{
  "project_info": {
    "project_number": "405778812722",
    "project_id": "smart-reply-ai-7b22a",
    "storage_bucket": "smart-reply-ai-7b22a.firebasestorage.app"
  },
  "client": [
    {
      "client_info": {
        "mobilesdk_app_id": "1:405778812722:android:3bb0af2b859563946c512b",
        "android_client_info": {
          "package_name": "com.myai.smartreplyai"
        }
      },
      "oauth_client": [],
      "api_key": [
        {
          "current_key": "AIzaSyA7qyaKRd22yqTU77-WMDkXEvESn6Fv-u8"
        }
      ],
      "services": {
        "appinvite_service": {
          "other_platform_oauth_client": []
        }
      }
    }
  ],
  "configuration_version": "1"
}